{
  "_class": "document",
  "assets": {
    "_class": "assetCollection",
    "colors": [
    ],
    "gradients": [
    ],
    "imageCollection": {
      "_class": "imageCollection",
      "images": {
      }
    },
    "images": [
    ]
  },
  "colorSpace": 0,
  "do_objectID": "9b4ad7b0-23bb-11e8-89b7-c986dd7dbf68",
  "foreignSymbols": [
  ],
  "layerSymbols": {
    "_class": "symbolContainer",
    "objects": [
    ]
  },
  "meta": {
    "appVersion": "49",
    "build": 51002,
    "version": 101
  },
  "pages": [
    "Page 1",
    "Symbols"
  ]
}